MANIFEST.in
README.rst
extraconfig.py
setup.py
django_extraconfig.egg-info/PKG-INFO
django_extraconfig.egg-info/SOURCES.txt
django_extraconfig.egg-info/dependency_links.txt
django_extraconfig.egg-info/top_level.txt