Metadata-Version: 1.0
Name: django-extraconfig
Version: 0.1.1
Summary: An entry-point based solution to extendthe Django configuration.
Home-page: http://github.com/pbs/django-extraconfig/
Author: Sever Banesiu
Author-email: banesiu.sever@gmail.com
License: BSD
Keywords: Django settings
Platform: UNKNOWN
